daktari/__init__.py
daktari/__main__.py
daktari/asdf.py
daktari/check.py
daktari/check_runner.py
daktari/check_sorter.py
daktari/check_utils.py
daktari/collection_utils.py
daktari/command_utils.py
daktari/config.py
daktari/file_utils.py
daktari/options.py
daktari/os.py
daktari/resource_utils.py
daktari/result_printer.py
daktari/test_asdf.py
daktari/test_check.py
daktari/test_check_factory.py
daktari/test_check_runner.py
daktari/test_check_sorter.py
daktari/test_check_utils.py
daktari/test_collection_utils.py
daktari/test_config.py
daktari/test_result_printer.py
daktari/test_version_utils.py
daktari/version_utils.py
daktari/checks/__init__.py
daktari/checks/android.py
daktari/checks/aws.py
daktari/checks/certs.py
daktari/checks/conan.py
daktari/checks/direnv.py
daktari/checks/docker.py
daktari/checks/etc_hosts.py
daktari/checks/files.py
daktari/checks/flutter.py
daktari/checks/git.py
daktari/checks/google.py
daktari/checks/intellij_idea.py
daktari/checks/java.py
daktari/checks/kubernetes.py
daktari/checks/misc.py
daktari/checks/nodejs.py
daktari/checks/onepassword.py
daktari/checks/python.py
daktari/checks/ssh.py
daktari/checks/terraform.py
daktari/checks/test_certs.py
daktari/checks/test_intellij_idea.py
daktari/checks/test_java.py
daktari/checks/test_misc.py
daktari/checks/test_onepassword.py
daktari/checks/test_ssh.py
daktari/checks/test_yarn.py
daktari/checks/xml.py
daktari/checks/yarn.py
daktari/resources/__init__.py
daktari/resources/daktari-local-template.yaml
daktari/resources/mock_cert.pem
daktari-0.0.302.dist-info/licenses/LICENSE.txt
daktari-0.0.302.dist-info/METADATA
daktari-0.0.302.dist-info/WHEEL
daktari-0.0.302.dist-info/entry_points.txt
daktari-0.0.302.dist-info/top_level.txt
daktari-0.0.302.dist-info/RECORD
