Metadata-Version: 2.4
Name: daktari
Version: 0.0.302
Summary: Assist in setting up and maintaining developer environments
Author-email: Matt Russell <matthew.russell@sonocent.com>
License: Copyright 2021 Sonocent Ltd
Project-URL: Homepage, https://github.com/sonocent/daktari
Requires-Python: >=3.9
License-File: LICENSE.txt
Requires-Dist: ansicolors==1.1.8
Requires-Dist: distro==1.9.0
Requires-Dist: pyfiglet==1.0.4
Requires-Dist: importlib_resources==6.5.2
Requires-Dist: packaging==25.0
Requires-Dist: setuptools==80.9.0
Requires-Dist: requests==2.32.5
Requires-Dist: responses==0.25.8
Requires-Dist: semver==3.0.4
Requires-Dist: python-hosts==1.1.2
Requires-Dist: PyYAML==6.0.3
Requires-Dist: types-PyYAML==6.0.12.20250915
Requires-Dist: pyobjc-core==12.0; sys_platform == "darwin"
Requires-Dist: pyobjc-framework-Cocoa==12.0; sys_platform == "darwin"
Requires-Dist: requests-unixsocket==0.4.1
Requires-Dist: dpath==2.2.0
Requires-Dist: pyOpenSSL==25.3.0
Requires-Dist: types-pyOpenSSL==24.1.0.20240722
Requires-Dist: pyclip==0.7.0
Requires-Dist: urllib3==2.6.3
Dynamic: license-file
